MANIFEST.in
README.rst
setup.py
collective/__init__.py
collective.z3cinspector.egg-info/PKG-INFO
collective.z3cinspector.egg-info/SOURCES.txt
collective.z3cinspector.egg-info/dependency_links.txt
collective.z3cinspector.egg-info/entry_points.txt
collective.z3cinspector.egg-info/namespace_packages.txt
collective.z3cinspector.egg-info/not-zip-safe
collective.z3cinspector.egg-info/requires.txt
collective.z3cinspector.egg-info/top_level.txt
collective/z3cinspector/__init__.py
collective/z3cinspector/config.py
collective/z3cinspector/configure.zcml
collective/z3cinspector/interfaces.py
collective/z3cinspector/registry.py
collective/z3cinspector/table.py
collective/z3cinspector/utils.py
collective/z3cinspector/views.py
collective/z3cinspector/resources/inspector.css
collective/z3cinspector/resources/inspector.js
collective/z3cinspector/resources/jquery.hotkeys-0.7.9.min.js
collective/z3cinspector/resources/jquery.min.js
collective/z3cinspector/resources/jquery.tools.min.js
collective/z3cinspector/resources/spinner.gif
collective/z3cinspector/resources/jquery-autocomplete/indicator.gif
collective/z3cinspector/resources/jquery-autocomplete/jquery.autocomplete-changelog.txt
collective/z3cinspector/resources/jquery-autocomplete/jquery.autocomplete.css
collective/z3cinspector/resources/jquery-autocomplete/jquery.autocomplete.js
collective/z3cinspector/resources/jquery-autocomplete/jquery.autocomplete.min.js
collective/z3cinspector/resources/jquery-autocomplete/jquery.autocomplete.pack.js
collective/z3cinspector/resources/jquery-autocomplete/todo
collective/z3cinspector/templates/inspect.pt
collective/z3cinspector/templates/results.pt
docs/HISTORY.txt