Metadata-Version: 1.0
Name: collective.z3cinspector
Version: 1.1
Summary: Zope3 component registry inspector
Home-page: http://github.com/collective/collective.z3cinspector
Author: Jonas Baumann, 4teamwork.ch
Author-email: mailto:info@4teamwork.ch
License: GPL2
Keywords: zope3 component registry inspector
Platform: UNKNOWN
Classifier: Framework :: Plone
Classifier: Framework :: Zope2
Classifier: Framework :: Zope3
Classifier: Programming Language :: Python
Classifier: Topic :: Software Development :: Libraries :: Python Modules
